brianmechanisms/ULMWGripWalker.py
brianmechanisms/__init__.py
brianmechanisms/appproximateStraightLineMechanisms.py
brianmechanisms/helpers.py
brianmechanisms/leggedTracks.py
brianmechanisms/leggedTracksTrue.py
brianmechanisms/locii.py
brianmechanisms/mirror.py
brianmechanisms/straightLineMechanisms.py
brianmechanisms/reciprocating/__init__.py
brianmechanisms/reciprocating/linearmotion/__init__.py
brianmechanisms/reciprocating/linearmotion/quickreturn/_1.py
brianmechanisms/reciprocating/linearmotion/quickreturn/_13.py
brianmechanisms/reciprocating/linearmotion/quickreturn/_14.py
brianmechanisms/reciprocating/linearmotion/quickreturn/_2.py
brianmechanisms/reciprocating/linearmotion/quickreturn/_22.py
brianmechanisms/reciprocating/linearmotion/quickreturn/_23.py
brianmechanisms/reciprocating/linearmotion/quickreturn/_25.py
brianmechanisms/reciprocating/linearmotion/quickreturn/_25.wrong.py
brianmechanisms/reciprocating/linearmotion/quickreturn/_26.py
brianmechanisms/reciprocating/linearmotion/quickreturn/_27.py
brianmechanisms/reciprocating/linearmotion/quickreturn/_28.py
brianmechanisms/reciprocating/linearmotion/quickreturn/_29.py
brianmechanisms/reciprocating/linearmotion/quickreturn/_30.py
brianmechanisms/reciprocating/linearmotion/quickreturn/_31.py
brianmechanisms/reciprocating/linearmotion/quickreturn/_32.py
brianmechanisms/reciprocating/linearmotion/quickreturn/_33.py
brianmechanisms/reciprocating/linearmotion/quickreturn/__2.py
brianmechanisms/reciprocating/linearmotion/quickreturn/__init__.py
brianmechanisms/reciprocating/rotarymotion/_3.py
brianmechanisms/reciprocating/rotarymotion/__init__.py
brianmechanisms/utils/__init__.py
brianmechanisms/utils/utils.py
brianmechanisms-0.1.30.dist-info/LICENSE
brianmechanisms-0.1.30.dist-info/METADATA
brianmechanisms-0.1.30.dist-info/WHEEL
brianmechanisms-0.1.30.dist-info/top_level.txt
brianmechanisms-0.1.30.dist-info/RECORD
