Metadata-Version: 2.1
Name: brianmechanisms
Version: 0.1.30
Summary: Python module for designing mechanisms and robots
Home-page: https://brianmechanisms.github.io
Author: Brian Onang'o
Author-email: surgbc@gmail.com
Project-URL: Homepage, https://github.com/brianmechanisms/brianmechanisms-designer
Project-URL: Issues, https://github.com/brianmechanisms/brianmechanisms-designer/issues
Classifier: Programming Language :: Python :: 3
Classifier: License :: OSI Approved :: Apache Software License
Classifier: Operating System :: OS Independent
Requires-Python: >=3.8
License-File: LICENSE
Requires-Dist: scikit-learn
Requires-Dist: numpy
Requires-Dist: matplotlib
